<?xml version="1.0" encoding="UTF-8"?>

<speak xmlns:xsi="http://www.w3.org/2001/XMLSchema-instance" version="1.0"
       xmlns="http://www.w3.org/2001/10/synthesis"
       xsi:schemaLocation="http://www.w3.org/2001/10/synthesis
                   http://www.w3.org/TR/speech-synthesis/synthesis.xsd"
       xml:lang="fr">

    <prosody rate="+25%">

        <if cond="To != 'maintain'">
            volons cap
                <value expr="To"/>
            <elseif cond="To == 'maintain'"/>
            maintenons cap
            <say-as>
                <value expr="flightHeading"/>
            </say-as>
        </if>

        <value expr="flightCallSign"/>
    </prosody>
</speak>